updator/__init__.py
updator/__main__.py
updator/astConverter.py
updator/astPatternBuilder.py
updator/astcompare.py
updator/dbInterface.py
updator/fsInterface.py
updator/updator.py
updator-0.1.6.dist-info/entry_points.txt
updator-0.1.6.dist-info/LICENSE
updator-0.1.6.dist-info/WHEEL
updator-0.1.6.dist-info/METADATA
updator-0.1.6.dist-info/RECORD
