Metadata-Version: 2.1
Name: updator
Version: 0.1.6
Summary: Automatically upgrade python libraries
Home-page: https://github.com/ShirAvr/updator.git
License: UNKNOWN
Author: Shir Avr
Author-email: shir@bhh.co.il
Requires-Python: >=3
Classifier: License :: OSI Approved :: MIT License
Requires-Dist: pymongo >=3.10.0
Requires-Dist: astor >=0.8.1
Requires-Dist: click >=7.1.1
Requires-Dist: tabulate >=0.8.7
